Workbook

Sheet Master Inventory
A1: No | B1: SKU | C1: Nama Produk | D1: Brand | E1: Sub-Kategori | F1: COGS per Unit (Rp) | G1: Target Margin Internal (%) | H1: Harga Internal (Modal+Margin) (Rp) | I1: Harga Jual Normal / RRP (Rp) | J1: Stock Awal (unit) | K1: Reorder Point (Min Stock) | L1: Gudang / Lokasi
A2: 1 | B2: SK-001 | C2: Facial Wash Gentle Foam 100ml | D2: LUMORA | E2: Skincare | F2: 16000 | G2: 0.62 | H2: =ROUND(F2/(1-G2),-3) -> 42000 | I2: 45000 | J2: 250 | K2: 40 | L2: Gudang Jakarta
A3: 2 | B3: SK-002 | C3: Toner Hydrating Rose 150ml | D3: LUMORA | E3: Skincare | F3: 22000 | G3: 0.62 | H3: =ROUND(F3/(1-G3),-3) -> 58000 | I3: 59000 | J3: 180 | K3: 35 | L3: Gudang Jakarta
A4: 3 | B4: SK-003 | C4: Serum Vitamin C 20ml | D4: LUMORA | E4: Skincare | F4: 35000 | G4: 0.62 | H4: =ROUND(F4/(1-G4),-3) -> 92000 | I4: 99000 | J4: 150 | K4: 30 | L4: Gudang Jakarta
A5: 4 | B5: SK-004 | C5: Serum Niacinamide 10% 20ml | D5: LUMORA | E5: Skincare | F5: 32000 | G5: 0.62 | H5: =ROUND(F5/(1-G5),-3) -> 84000 | I5: 89000 | J5: 200 | K5: 40 | L5: Gudang Jakarta
A6: 5 | B6: SK-005 | C6: Moisturizer Gel Cream 40g | D6: LUMORA | E6: Skincare | F6: 28000 | G6: 0.62 | H6: =ROUND(F6/(1-G6),-3) -> 74000 | I6: 79000 | J6: 160 | K6: 30 | L6: Gudang Bandung
A7: 6 | B7: SK-006 | C7: Sunscreen SPF50 PA+++ 40ml | D7: LUMORA | E7: Skincare | F7: 30000 | G7: 0.62 | H7: =ROUND(F7/(1-G7),-3) -> 79000 | I7: 85000 | J7: 300 | K7: 50 | L7: Gudang Jakarta
A8: 7 | B8: SK-007 | C8: Eye Cream Anti Aging 15ml | D8: LUMORA | E8: Skincare | F8: 38000 | G8: 0.62 | H8: =ROUND(F8/(1-G8),-3) -> 100000 | I8: 105000 | J8: 30 | K8: 20 | L8: Gudang Bandung
A9: 8 | B9: SK-008 | C9: Sheet Mask Brightening (Box 5pcs) | D9: LUMORA | E9: Skincare | F9: 20000 | G9: 0.62 | H9: =ROUND(F9/(1-G9),-3) -> 53000 | I9: 55000 | J9: 220 | K9: 40 | L9: Gudang Jakarta
A10: 9 | B10: MU-001 | C10: Lip Tint Velvet Matte | D10: LUMORA | E10: Makeup | F10: 14000 | G10: 0.6 | H10: =ROUND(F10/(1-G10),-3) -> 35000 | I10: 39000 | J10: 280 | K10: 50 | L10: Gudang Jakarta
A11: 10 | B11: MU-002 | C11: Lip Cream Matte Long Lasting | D11: LUMORA | E11: Makeup | F11: 15000 | G11: 0.6 | H11: =ROUND(F11/(1-G11),-3) -> 38000 | I11: 42000 | J11: 260 | K11: 45 | L11: Gudang Jakarta
A12: 11 | B12: MU-003 | C12: Cushion Foundation SPF35 | D12: LUMORA | E12: Makeup | F12: 45000 | G12: 0.6 | H12: =ROUND(F12/(1-G12),-3) -> 112000 | I12: 135000 | J12: 140 | K12: 25 | L12: Gudang Bandung
A13: 12 | B13: MU-004 | C13: Compact Powder Matte Finish | D13: LUMORA | E13: Makeup | F13: 25000 | G13: 0.6 | H13: =ROUND(F13/(1-G13),-3) -> 62000 | I13: 69000 | J13: 130 | K13: 25 | L13: Gudang Bandung
... A26: 25 | B26: FR-002 | C26: Eau de Parfum 50ml | D26: LUMORA | E26: Fragrance | F26: 85000 | G26: 0.65 | H26: =ROUND(F26/(1-G26),-3) -> 243000 | I26: 259000 | J26: 50 | K26: 10 | L26: Gudang Bandung

Sheet Sales - TikTok
A1: No | B1: Tanggal Transaksi | C1: Platform | D1: Order ID | E1: SKU | F1: Nama Produk | G1: Qty Terjual | H1: Harga Jual Normal /Unit (Rp) | I1: Diskon (%) | J1: Harga Jual Net /Unit (Rp) | K1: Total Revenue Net (Rp) | L1: COGS per Unit (Rp) | M1: Total COGS (Rp) | N1: Margin (Rp) | O1: Margin (%) | P1: Status Margin (vs COGS) | Q1: Fee Platform (%) | R1: Total Fee Platform (Rp) | S1: Revenue Diterima Setelah Fee (Rp) | T1: Margin Setelah Fee (Rp) | U1: Margin Setelah Fee (%) | V1: Status Rugi Setelah Fee
A2: 1 | B2: 46266 | C2: TikTok | D2: TTK-2609-0003 | E2: SK-003 | F2: =VLOOKUP(E2,'Master Inventory'!$B$2:$L$26,2,FALSE) -> Serum Vitamin C 20ml | G2: 2 | H2: 93500 | I2: 0.21 | J2: 73900 | K2: =J2*G2 -> 147800 | L2: =VLOOKUP(E2,'Master Inventory'!$B$2:$L$26,5,FALSE) -> 35000 | M2: =L2*G2 -> 70000 | N2: =K2-M2 -> 77800 | O2: =IFERROR(N2/K2,0) -> 0.526387 | P2: =IF(J2<L2,"BELOW COGS","OK") -> OK | Q2: 0.07 | R2: =K2*Q2 -> 10346 | S2: =K2-R2 -> 137454 | T2: =S2-M2 -> 67454 | U2: =IFERROR(T2/S2,0) -> 0.490739 | V2: =IF(T2<0,"RUGI SETELAH FEE","OK") -> OK
A3: 2 | B3: 46266 | C3: TikTok | D3: TTK-2609-0027 | E3: HC-005 | F3: =VLOOKUP(E3,'Master Inventory'!$B$2:$L$26,2,FALSE) -> Hair Vitamin Ampoule (Box 6pcs) | G3: 3 | H3: 72000 | I3: 0.63 | J3: 26600 | K3: =J3*G3 -> 79800 | L3: =VLOOKUP(E3,'Master Inventory'!$B$2:$L$26,5,FALSE) -> 26000 | M3: =L3*G3 -> 78000 | N3: =K3-M3 -> 1800 | O3: =IFERROR(N3/K3,0) -> 0.022556 | P3: =IF(J3<L3,"BELOW COGS","OK") -> OK | Q3: 0.07 | R3: =K3*Q3 -> 5586 | S3: =K3-R3 -> 74214 | T3: =S3-M3 -> -3786 | U3: =IFERROR(T3/S3,0) -> -0.051015 | V3: =IF(T3<0,"RUGI SETELAH FEE","OK") -> RUGI SETELAH FEE
A4: 3 | B4: 46266 | C4: TikTok | D4: TTK-2609-0062 | E4: MU-003 | F4: =VLOOKUP(E4,'Master Inventory'!$B$2:$L$26,2,FALSE) -> Cushion Foundation SPF35 | G4: 2 | H4: 138500 | I4: 0.72 | J4: 38800 | K4: =J4*G4 -> 77600 | L4: =VLOOKUP(E4,'Master Inventory'!$B$2:$L$26,5,FALSE) -> 45000 | M4: =L4*G4 -> 90000 | N4: =K4-M4 -> -12400 | O4: =IFERROR(N4/K4,0) -> -0.159794 | P4: =IF(J4<L4,"BELOW COGS","OK") -> BELOW COGS | Q4: 0.07 | R4: =K4*Q4 -> 5432 | S4: =K4-R4 -> 72168 | T4: =S4-M4 -> -17832 | U4: =IFERROR(T4/S4,0) -> -0.24709 | V4: =IF(T4<0,"RUGI SETELAH FEE","OK") -> RUGI SETELAH FEE
A5: 4 | B5: 46266 | C5: TikTok | D5: TTK-2609-0072 | E5: BC-002 | F5: =VLOOKUP(E5,'Master Inventory'!$B$2:$L$26,2,FALSE) -> Body Scrub Coffee 200g | G5: 2 | H5: 47000 | I5: 0.57 | J5: 20200 | K5: =J5*G5 -> 40400 | L5: =VLOOKUP(E5,'Master Inventory'!$B$2:$L$26,5,FALSE) -> 17000 | M5: =L5*G5 -> 34000 | N5: =K5-M5 -> 6400 | O5: =IFERROR(N5/K5,0) -> 0.158416 | P5: =IF(J5<L5,"BELOW COGS","OK") -> OK | Q5: 0.07 | R5: =K5*Q5 -> 2828 | S5: =K5-R5 -> 37572 | T5: =S5-M5 -> 3572 | U5: =IFERROR(T5/S5,0) -> 0.095071 | V5: =IF(T5<0,"RUGI SETELAH FEE","OK") -> OK
A6: 5 | B6: 46266 | C6: TikTok | D6: TTK-2609-0090 | E6: FR-002 | F6: =VLOOKUP(E6,'Master Inventory'!$B$2:$L$26,2,FALSE) -> Eau de Parfum 50ml | G6: 1 | H6: 273500 | I6: 0.73 | J6: 73800 | K6: =J6*G6 -> 73800 | L6: =VLOOKUP(E6,'Master Inventory'!$B$2:$L$26,5,FALSE) -> 85000 | M6: =L6*G6 -> 85000 | N6: =K6-M6 -> -11200 | O6: =IFERROR(N6/K6,0) -> -0.151762 | P6: =IF(J6<L6,"BELOW COGS","OK") -> BELOW COGS | Q6: 0.07 | R6: =K6*Q6 -> 5166 | S6: =K6-R6 -> 68634 | T6: =S6-M6 -> -16366 | U6: =IFERROR(T6/S6,0) -> -0.238453 | V6: =IF(T6<0,"RUGI SETELAH FEE","OK") -> RUGI SETELAH FEE
A7: 6 | B7: 46267 | C7: TikTok | D7: TTK-2609-0035 | E7: SK-008 | F7: =VLOOKUP(E7,'Master Inventory'!$B$2:$L$26,2,FALSE) -> Sheet Mask Brightening (Box 5pcs) | G7: 1 | H7: 59500 | I7: 0.01 | J7: 58900 | K7: =J7*G7 -> 58900 | L7: =VLOOKUP(E7,'Master Inventory'!$B$2:$L$26,5,FALSE) -> 20000 | M7: =L7*G7 -> 20000 | N7: =K7-M7 -> 38900 | O7: =IFERROR(N7/K7,0) -> 0.660441 | P7: =IF(J7<L7,"BELOW COGS","OK") -> OK | Q7: 0.07 | R7: =K7*Q7 -> 4123 | S7: =K7-R7 -> 54777 | T7: =S7-M7 -> 34777 | U7: =IFERROR(T7/S7,0) -> 0.634883 | V7: =IF(T7<0,"RUGI SETELAH FEE","OK") -> OK
A8: 7 | B8: 46267 | C8: TikTok | D8: TTK-2609-0077 | E8: BC-003 | F8: =VLOOKUP(E8,'Master Inventory'!$B$2:$L$26,2,FALSE) -> Body Mist Fresh Bloom 100ml | G8: 4 | H8: 49500 | I8: 0.04 | J8: 47500 | K8: =J8*G8 -> 190000 | L8: =VLOOKUP(E8,'Master Inventory'!$B$2:$L$26,5,FALSE) -> 19000 | M8: =L8*G8 -> 76000 | N8: =K8-M8 -> 114000 | O8: =IFERROR(N8/K8,0) -> 0.6 | P8: =IF(J8<L8,"BELOW COGS","OK") -> OK | Q8: 0.07 | R8: =K8*Q8 -> 13300 | S8: =K8-R8 -> 176700 | T8: =S8-M8 -> 100700 | U8: =IFERROR(T8/S8,0) -> 0.569892 | V8: =IF(T8<0,"RUGI SETELAH FEE","OK") -> OK
A9: 8 | B9: 46268 | C9: TikTok | D9: TTK-2609-0029 | E9: FR-001 | F9: =VLOOKUP(E9,'Master Inventory'!$B$2:$L$26,2,FALSE) -> Eau de Toilette 30ml | G9: 4 | H9: 190500 | I9: 0.04 | J9: 182900 | K9: =J9*G9 -> 731600 | L9: =VLOOKUP(E9,'Master Inventory'!$B$2:$L$26,5,FALSE) -> 55000 | M9: =L9*G9 -> 220000 | N9: =K9-M9 -> 511600 | O9: =IFERROR(N9/K9,0) -> 0.699289 | P9: =IF(J9<L9,"BELOW COGS","OK") -> OK | Q9: 0.07 | R9: =K9*Q9 -> 51212 | S9: =K9-R9 -> 680388 | T9: =S9-M9 -> 460388 | U9: =IFERROR(T9/S9,0) -> 0.676655 | V9: =IF(T9<0,"RUGI SETELAH FEE","OK") -> OK
A10: 9 | B10: 46269 | C10: TikTok | D10: TTK-2609-0002 | E10: BC-002 | F10: =VLOOKUP(E10,'Master Inventory'!$B$2:$L$26,2,FALSE) -> Body Scrub Coffee 200g | G10: 6 | H10: 52000 | I10: 0.65 | J10: 18200 | K10: =J10*G10 -> 109200 | L10: =VLOOKUP(E10,'Master Inventory'!$B$2:$L$26,5,FALSE) -> 17000 | M10: =L10*G10 -> 102000 | N10: =K10-M10 -> 7200 | O10: =IFERROR(N10/K10,0) -> 0.065934 | P10: =IF(J10<L10,"BELOW COGS","OK") -> OK | Q10: 0.07 | R10: =K10*Q10 -> 7644 | S10: =K10-R10 -> 101556 | T10: =S10-M10 -> -444 | U10: =IFERROR(T10/S10,0) -> -0.004372 | V10: =IF(T10<0,"RUGI SETELAH FEE","OK") -> RUGI SETELAH FEE
A11: 10 | B11: 46269 | C11: TikTok | D11: TTK-2609-0025 | E11: BC-001 | F11: =VLOOKUP(E11,'Master Inventory'!$B$2:$L$26,2,FALSE) -> Body Lotion Brightening 200ml | G11: 3 | H11: 48000 | I11: 0.14 | J11: 41300 | K11: =J11*G11 -> 123900 | L11: =VLOOKUP(E11,'Master Inventory'!$B$2:$L$26,5,FALSE) -> 16000 | M11: =L11*G11 -> 48000 | N11: =K11-M11 -> 75900 | O11: =IFERROR(N11/K11,0) -> 0.612591 | P11: =IF(J11<L11,"BELOW COGS","OK") -> OK | Q11: 0.07 | R11: =K11*Q11 -> 8673 | S11: =K11-R11 -> 115227 | T11: =S11-M11 -> 67227 | U11: =IFERROR(T11/S11,0) -> 0.583431 | V11: =IF(T11<0,"RUGI SETELAH FEE","OK") -> OK
A12: 11 | B12: 46269 | C12: TikTok | D12: TTK-2609-0055 | E12: SK-003 | F12: =VLOOKUP(E12,'Master Inventory'!$B$2:$L$26,2,FALSE) -> Serum Vitamin C 20ml | G12: 5 | H12: 93500 | I12: 0.76 | J12: 22400 | K12: =J12*G12 -> 112000 | L12: =VLOOKUP(E12,'Master Inventory'!$B$2:$L$26,5,FALSE) -> 35000 | M12: =L12*G12 -> 175000 | N12: =K12-M12 -> -63000 | O12: =IFERROR(N12/K12,0) -> -0.5625 | P12: =IF(J12<L12,"BELOW COGS","OK") -> BELOW COGS | Q12: 0.07 | R12: =K12*Q12 -> 7840 | S12: =K12-R12 -> 104160 | T12: =S12-M12 -> -70840 | U12: =IFERROR(T12/S12,0) -> -0.680108 | V12: =IF(T12<0,"RUGI SETELAH FEE","OK") -> RUGI SETELAH FEE
A13: 12 | B13: 46270 | C13: TikTok | D13: TTK-2609-0019 | E13: HC-002 | F13: =VLOOKUP(E13,'Master Inventory'!$B$2:$L$26,2,FALSE) -> Shampoo Anti Hairfall 300ml | G13: 4 | H13: 45000 | I13: 0.58 | J13: 18900 | K13: =J13*G13 -> 75600 | L13: =VLOOKUP(E13,'Master Inventory'!$B$2:$L$26,5,FALSE) -> 18000 | M13: =L13*G13 -> 72000 | N13: =K13-M13 -> 3600 | O13: =IFERROR(N13/K13,0) -> 0.047619 | P13: =IF(J13<L13,"BELOW COGS","OK") -> OK | Q13: 0.07 | R13: =K13*Q13 -> 5292 | S13: =K13-R13 -> 70308 | T13: =S13-M13 -> -1692 | U13: =IFERROR(T13/S13,0) -> -0.024066 | V13: =IF(T13<0,"RUGI SETELAH FEE","OK") -> RUGI SETELAH FEE
... A101: 100 | B101: 46295 | C101: TikTok | D101: TTK-2609-0094 | E101: HC-003 | F101: =VLOOKUP(E101,'Master Inventory'!$B$2:$L$26,2,FALSE) -> Conditioner Repair 300ml | G101: 4 | H101: 53000 | I101: 0.04 | J101: 50900 | K101: =J101*G101 -> 203600 | L101: =VLOOKUP(E101,'Master Inventory'!$B$2:$L$26,5,FALSE) -> 18000 | M101: =L101*G101 -> 72000 | N101: =K101-M101 -> 131600 | O101: =IFERROR(N101/K101,0) -> 0.646365 | P101: =IF(J101<L101,"BELOW COGS","OK") -> OK | Q101: 0.07 | R101: =K101*Q101 -> 14252 | S101: =K101-R101 -> 189348 | T101: =S101-M101 -> 117348 | U101: =IFERROR(T101/S101,0) -> 0.619748 | V101: =IF(T101<0,"RUGI SETELAH FEE","OK") -> OK
F102: TOTAL | G102: =SUM(G2:G101) -> 323 | K102: =SUM(K2:K101) -> 17907400 | M102: =SUM(M2:M101) -> 9024000 | N102: =SUM(N2:N101) -> 8883400 | O102: =IFERROR(N102/K102,0) -> 0.496074 | P102: =COUNTIF(P2:P101,"BELOW COGS")&" transaksi" -> 23 transaksi | R102: =SUM(R2:R101) -> 1253518 | S102: =SUM(S2:S101) -> 16653882 | T102: =SUM(T2:T101) -> 7629882 | U102: =IFERROR(T102/S102,0) -> 0.458144 | V102: =COUNTIF(V2:V101,"RUGI SETELAH FEE")&" transaksi" -> 32 transaksi

Sheet Sales - Shopee
A1: No | B1: Tanggal Transaksi | C1: Platform | D1: Order ID | E1: SKU | F1: Nama Produk | G1: Qty Terjual | H1: Harga Jual Normal /Unit (Rp) | I1: Diskon (%) | J1: Harga Jual Net /Unit (Rp) | K1: Total Revenue Net (Rp) | L1: COGS per Unit (Rp) | M1: Total COGS (Rp) | N1: Margin (Rp) | O1: Margin (%) | P1: Status Margin (vs COGS) | Q1: Fee Platform (%) | R1: Total Fee Platform (Rp) | S1: Revenue Diterima Setelah Fee (Rp) | T1: Margin Setelah Fee (Rp) | U1: Margin Setelah Fee (%) | V1: Status Rugi Setelah Fee
A2: 1 | B2: 46266 | C2: Shopee | D2: SHP-2609-0068 | E2: MU-002 | F2: =VLOOKUP(E2,'Master Inventory'!$B$2:$L$26,2,FALSE) -> Lip Cream Matte Long Lasting | G2: 6 | H2: 40500 | I2: 0.3 | J2: 28400 | K2: =J2*G2 -> 170400 | L2: =VLOOKUP(E2,'Master Inventory'!$B$2:$L$26,5,FALSE) -> 15000 | M2: =L2*G2 -> 90000 | N2: =K2-M2 -> 80400 | O2: =IFERROR(N2/K2,0) -> 0.471831 | P2: =IF(J2<L2,"BELOW COGS","OK") -> OK | Q2: 0.06 | R2: =K2*Q2 -> 10224 | S2: =K2-R2 -> 160176 | T2: =S2-M2 -> 70176 | U2: =IFERROR(T2/S2,0) -> 0.438118 | V2: =IF(T2<0,"RUGI SETELAH FEE","OK") -> OK
A3: 2 | B3: 46267 | C3: Shopee | D3: SHP-2609-0010 | E3: FR-002 | F3: =VLOOKUP(E3,'Master Inventory'!$B$2:$L$26,2,FALSE) -> Eau de Parfum 50ml | G3: 1 | H3: 282500 | I3: 0.55 | J3: 127100 | K3: =J3*G3 -> 127100 | L3: =VLOOKUP(E3,'Master Inventory'!$B$2:$L$26,5,FALSE) -> 85000 | M3: =L3*G3 -> 85000 | N3: =K3-M3 -> 42100 | O3: =IFERROR(N3/K3,0) -> 0.331235 | P3: =IF(J3<L3,"BELOW COGS","OK") -> OK | Q3: 0.06 | R3: =K3*Q3 -> 7626 | S3: =K3-R3 -> 119474 | T3: =S3-M3 -> 34474 | U3: =IFERROR(T3/S3,0) -> 0.288548 | V3: =IF(T3<0,"RUGI SETELAH FEE","OK") -> OK
A4: 3 | B4: 46267 | C4: Shopee | D4: SHP-2609-0038 | E4: SK-005 | F4: =VLOOKUP(E4,'Master Inventory'!$B$2:$L$26,2,FALSE) -> Moisturizer Gel Cream 40g | G4: 2 | H4: 84000 | I4: 0.01 | J4: 83200 | K4: =J4*G4 -> 166400 | L4: =VLOOKUP(E4,'Master Inventory'!$B$2:$L$26,5,FALSE) -> 28000 | M4: =L4*G4 -> 56000 | N4: =K4-M4 -> 110400 | O4: =IFERROR(N4/K4,0) -> 0.663462 | P4: =IF(J4<L4,"BELOW COGS","OK") -> OK | Q4: 0.06 | R4: =K4*Q4 -> 9984 | S4: =K4-R4 -> 156416 | T4: =S4-M4 -> 100416 | U4: =IFERROR(T4/S4,0) -> 0.64198 | V4: =IF(T4<0,"RUGI SETELAH FEE","OK") -> OK
A5: 4 | B5: 46268 | C5: Shopee | D5: SHP-2609-0006 | E5: BC-001 | F5: =VLOOKUP(E5,'Master Inventory'!$B$2:$L$26,2,FALSE) -> Body Lotion Brightening 200ml | G5: 4 | H5: 41500 | I5: 0.11 | J5: 36900 | K5: =J5*G5 -> 147600 | L5: =VLOOKUP(E5,'Master Inventory'!$B$2:$L$26,5,FALSE) -> 16000 | M5: =L5*G5 -> 64000 | N5: =K5-M5 -> 83600 | O5: =IFERROR(N5/K5,0) -> 0.566396 | P5: =IF(J5<L5,"BELOW COGS","OK") -> OK | Q5: 0.06 | R5: =K5*Q5 -> 8856 | S5: =K5-R5 -> 138744 | T5: =S5-M5 -> 74744 | U5: =IFERROR(T5/S5,0) -> 0.538719 | V5: =IF(T5<0,"RUGI SETELAH FEE","OK") -> OK
A6: 5 | B6: 46268 | C6: Shopee | D6: SHP-2609-0022 | E6: MU-001 | F6: =VLOOKUP(E6,'Master Inventory'!$B$2:$L$26,2,FALSE) -> Lip Tint Velvet Matte | G6: 4 | H6: 37000 | I6: 0.22 | J6: 28900 | K6: =J6*G6 -> 115600 | L6: =VLOOKUP(E6,'Master Inventory'!$B$2:$L$26,5,FALSE) -> 14000 | M6: =L6*G6 -> 56000 | N6: =K6-M6 -> 59600 | O6: =IFERROR(N6/K6,0) -> 0.515571 | P6: =IF(J6<L6,"BELOW COGS","OK") -> OK | Q6: 0.06 | R6: =K6*Q6 -> 6936 | S6: =K6-R6 -> 108664 | T6: =S6-M6 -> 52664 | U6: =IFERROR(T6/S6,0) -> 0.48465 | V6: =IF(T6<0,"RUGI SETELAH FEE","OK") -> OK
A7: 6 | B7: 46268 | C7: Shopee | D7: SHP-2609-0055 | E7: HC-001 | F7: =VLOOKUP(E7,'Master Inventory'!$B$2:$L$26,2,FALSE) -> Hair Serum Anti Frizz 60ml | G7: 3 | H7: 67500 | I7: 0.57 | J7: 29000 | K7: =J7*G7 -> 87000 | L7: =VLOOKUP(E7,'Master Inventory'!$B$2:$L$26,5,FALSE) -> 24000 | M7: =L7*G7 -> 72000 | N7: =K7-M7 -> 15000 | O7: =IFERROR(N7/K7,0) -> 0.172414 | P7: =IF(J7<L7,"BELOW COGS","OK") -> OK | Q7: 0.06 | R7: =K7*Q7 -> 5220 | S7: =K7-R7 -> 81780 | T7: =S7-M7 -> 9780 | U7: =IFERROR(T7/S7,0) -> 0.119589 | V7: =IF(T7<0,"RUGI SETELAH FEE","OK") -> OK
A8: 7 | B8: 46268 | C8: Shopee | D8: SHP-2609-0076 | E8: HC-001 | F8: =VLOOKUP(E8,'Master Inventory'!$B$2:$L$26,2,FALSE) -> Hair Serum Anti Frizz 60ml | G8: 3 | H8: 67000 | I8: 0.23 | J8: 51600 | K8: =J8*G8 -> 154800 | L8: =VLOOKUP(E8,'Master Inventory'!$B$2:$L$26,5,FALSE) -> 24000 | M8: =L8*G8 -> 72000 | N8: =K8-M8 -> 82800 | O8: =IFERROR(N8/K8,0) -> 0.534884 | P8: =IF(J8<L8,"BELOW COGS","OK") -> OK | Q8: 0.06 | R8: =K8*Q8 -> 9288 | S8: =K8-R8 -> 145512 | T8: =S8-M8 -> 73512 | U8: =IFERROR(T8/S8,0) -> 0.505195 | V8: =IF(T8<0,"RUGI SETELAH FEE","OK") -> OK
A9: 8 | B9: 46268 | C9: Shopee | D9: SHP-2609-0098 | E9: SK-005 | F9: =VLOOKUP(E9,'Master Inventory'!$B$2:$L$26,2,FALSE) -> Moisturizer Gel Cream 40g | G9: 2 | H9: 84500 | I9: 0.08 | J9: 77700 | K9: =J9*G9 -> 155400 | L9: =VLOOKUP(E9,'Master Inventory'!$B$2:$L$26,5,FALSE) -> 28000 | M9: =L9*G9 -> 56000 | N9: =K9-M9 -> 99400 | O9: =IFERROR(N9/K9,0) -> 0.63964 | P9: =IF(J9<L9,"BELOW COGS","OK") -> OK | Q9: 0.06 | R9: =K9*Q9 -> 9324 | S9: =K9-R9 -> 146076 | T9: =S9-M9 -> 90076 | U9: =IFERROR(T9/S9,0) -> 0.616638 | V9: =IF(T9<0,"RUGI SETELAH FEE","OK") -> OK
A10: 9 | B10: 46269 | C10: Shopee | D10: SHP-2609-0042 | E10: FR-002 | F10: =VLOOKUP(E10,'Master Inventory'!$B$2:$L$26,2,FALSE) -> Eau de Parfum 50ml | G10: 2 | H10: 265500 | I10: 0.57 | J10: 114200 | K10: =J10*G10 -> 228400 | L10: =VLOOKUP(E10,'Master Inventory'!$B$2:$L$26,5,FALSE) -> 85000 | M10: =L10*G10 -> 170000 | N10: =K10-M10 -> 58400 | O10: =IFERROR(N10/K10,0) -> 0.255692 | P10: =IF(J10<L10,"BELOW COGS","OK") -> OK | Q10: 0.06 | R10: =K10*Q10 -> 13704 | S10: =K10-R10 -> 214696 | T10: =S10-M10 -> 44696 | U10: =IFERROR(T10/S10,0) -> 0.208183 | V10: =IF(T10<0,"RUGI SETELAH FEE","OK") -> OK
A11: 10 | B11: 46269 | C11: Shopee | D11: SHP-2609-0049 | E11: MU-007 | F11: =VLOOKUP(E11,'Master Inventory'!$B$2:$L$26,2,FALSE) -> Makeup Setting Spray 100ml | G11: 6 | H11: 62500 | I11: 0.15 | J11: 53100 | K11: =J11*G11 -> 318600 | L11: =VLOOKUP(E11,'Master Inventory'!$B$2:$L$26,5,FALSE) -> 22000 | M11: =L11*G11 -> 132000 | N11: =K11-M11 -> 186600 | O11: =IFERROR(N11/K11,0) -> 0.585687 | P11: =IF(J11<L11,"BELOW COGS","OK") -> OK | Q11: 0.06 | R11: =K11*Q11 -> 19116 | S11: =K11-R11 -> 299484 | T11: =S11-M11 -> 167484 | U11: =IFERROR(T11/S11,0) -> 0.559242 | V11: =IF(T11<0,"RUGI SETELAH FEE","OK") -> OK
A12: 11 | B12: 46269 | C12: Shopee | D12: SHP-2609-0058 | E12: FR-002 | F12: =VLOOKUP(E12,'Master Inventory'!$B$2:$L$26,2,FALSE) -> Eau de Parfum 50ml | G12: 4 | H12: 278000 | I12: 0 | J12: 278000 | K12: =J12*G12 -> 1112000 | L12: =VLOOKUP(E12,'Master Inventory'!$B$2:$L$26,5,FALSE) -> 85000 | M12: =L12*G12 -> 340000 | N12: =K12-M12 -> 772000 | O12: =IFERROR(N12/K12,0) -> 0.694245 | P12: =IF(J12<L12,"BELOW COGS","OK") -> OK | Q12: 0.06 | R12: =K12*Q12 -> 66720 | S12: =K12-R12 -> 1045280 | T12: =S12-M12 -> 705280 | U12: =IFERROR(T12/S12,0) -> 0.674728 | V12: =IF(T12<0,"RUGI SETELAH FEE","OK") -> OK
A13: 12 | B13: 46269 | C13: Shopee | D13: SHP-2609-0064 | E13: BC-001 | F13: =VLOOKUP(E13,'Master Inventory'!$B$2:$L$26,2,FALSE) -> Body Lotion Brightening 200ml | G13: 2 | H13: 45000 | I13: 0.04 | J13: 43200 | K13: =J13*G13 -> 86400 | L13: =VLOOKUP(E13,'Master Inventory'!$B$2:$L$26,5,FALSE) -> 16000 | M13: =L13*G13 -> 32000 | N13: =K13-M13 -> 54400 | O13: =IFERROR(N13/K13,0) -> 0.62963 | P13: =IF(J13<L13,"BELOW COGS","OK") -> OK | Q13: 0.06 | R13: =K13*Q13 -> 5184 | S13: =K13-R13 -> 81216 | T13: =S13-M13 -> 49216 | U13: =IFERROR(T13/S13,0) -> 0.605989 | V13: =IF(T13<0,"RUGI SETELAH FEE","OK") -> OK
... A101: 100 | B101: 46293 | C101: Shopee | D101: SHP-2609-0099 | E101: HC-003 | F101: =VLOOKUP(E101,'Master Inventory'!$B$2:$L$26,2,FALSE) -> Conditioner Repair 300ml | G101: 3 | H101: 45000 | I101: 0.15 | J101: 38200 | K101: =J101*G101 -> 114600 | L101: =VLOOKUP(E101,'Master Inventory'!$B$2:$L$26,5,FALSE) -> 18000 | M101: =L101*G101 -> 54000 | N101: =K101-M101 -> 60600 | O101: =IFERROR(N101/K101,0) -> 0.528796 | P101: =IF(J101<L101,"BELOW COGS","OK") -> OK | Q101: 0.06 | R101: =K101*Q101 -> 6876 | S101: =K101-R101 -> 107724 | T101: =S101-M101 -> 53724 | U101: =IFERROR(T101/S101,0) -> 0.498719 | V101: =IF(T101<0,"RUGI SETELAH FEE","OK") -> OK
F102: TOTAL | G102: =SUM(G2:G101) -> 337 | K102: =SUM(K2:K101) -> 21024300 | M102: =SUM(M2:M101) -> 10556000 | N102: =SUM(N2:N101) -> 10468300 | O102: =IFERROR(N102/K102,0) -> 0.497914 | P102: =COUNTIF(P2:P101,"BELOW COGS")&" transaksi" -> 19 transaksi | R102: =SUM(R2:R101) -> 1261458 | S102: =SUM(S2:S101) -> 19762842 | T102: =SUM(T2:T101) -> 9206842 | U102: =IFERROR(T102/S102,0) -> 0.465866 | V102: =COUNTIF(V2:V101,"RUGI SETELAH FEE")&" transaksi" -> 22 transaksi

Sheet Stock Check
A1: No | B1: SKU | C1: Nama Produk | D1: Stock Awal (unit) | E1: Terjual TikTok (unit) | F1: Terjual Shopee (unit) | G1: Total Terjual (unit) | H1: Sisa Stock (unit) | I1: Status Stock
A2: 1 | B2: SK-001 | C2: ='Master Inventory'!C2 -> Facial Wash Gentle Foam 100ml | D2: ='Master Inventory'!J2 -> 250 | E2: =SUMIF('Sales - TikTok'!$E$2:$E$101,B2,'Sales - TikTok'!$G$2:$G$101) -> 2 | F2: =SUMIF('Sales - Shopee'!$E$2:$E$101,B2,'Sales - Shopee'!$G$2:$G$101) -> 23 | G2: =E2+F2 -> 25 | H2: =D2-G2 -> 225 | I2: =IF(H2<=0,"OUT OF STOCK",IF(H2<='Master Inventory'!K2,"LOW STOCK","AMAN")) -> AMAN
A3: 2 | B3: SK-002 | C3: ='Master Inventory'!C3 -> Toner Hydrating Rose 150ml | D3: ='Master Inventory'!J3 -> 180 | E3: =SUMIF('Sales - TikTok'!$E$2:$E$101,B3,'Sales - TikTok'!$G$2:$G$101) -> 7 | F3: =SUMIF('Sales - Shopee'!$E$2:$E$101,B3,'Sales - Shopee'!$G$2:$G$101) -> 12 | G3: =E3+F3 -> 19 | H3: =D3-G3 -> 161 | I3: =IF(H3<=0,"OUT OF STOCK",IF(H3<='Master Inventory'!K3,"LOW STOCK","AMAN")) -> AMAN
A4: 3 | B4: SK-003 | C4: ='Master Inventory'!C4 -> Serum Vitamin C 20ml | D4: ='Master Inventory'!J4 -> 150 | E4: =SUMIF('Sales - TikTok'!$E$2:$E$101,B4,'Sales - TikTok'!$G$2:$G$101) -> 25 | F4: =SUMIF('Sales - Shopee'!$E$2:$E$101,B4,'Sales - Shopee'!$G$2:$G$101) -> 2 | G4: =E4+F4 -> 27 | H4: =D4-G4 -> 123 | I4: =IF(H4<=0,"OUT OF STOCK",IF(H4<='Master Inventory'!K4,"LOW STOCK","AMAN")) -> AMAN
A5: 4 | B5: SK-004 | C5: ='Master Inventory'!C5 -> Serum Niacinamide 10% 20ml | D5: ='Master Inventory'!J5 -> 200 | E5: =SUMIF('Sales - TikTok'!$E$2:$E$101,B5,'Sales - TikTok'!$G$2:$G$101) -> 12 | F5: =SUMIF('Sales - Shopee'!$E$2:$E$101,B5,'Sales - Shopee'!$G$2:$G$101) -> 12 | G5: =E5+F5 -> 24 | H5: =D5-G5 -> 176 | I5: =IF(H5<=0,"OUT OF STOCK",IF(H5<='Master Inventory'!K5,"LOW STOCK","AMAN")) -> AMAN
A6: 5 | B6: SK-005 | C6: ='Master Inventory'!C6 -> Moisturizer Gel Cream 40g | D6: ='Master Inventory'!J6 -> 160 | E6: =SUMIF('Sales - TikTok'!$E$2:$E$101,B6,'Sales - TikTok'!$G$2:$G$101) -> 18 | F6: =SUMIF('Sales - Shopee'!$E$2:$E$101,B6,'Sales - Shopee'!$G$2:$G$101) -> 10 | G6: =E6+F6 -> 28 | H6: =D6-G6 -> 132 | I6: =IF(H6<=0,"OUT OF STOCK",IF(H6<='Master Inventory'!K6,"LOW STOCK","AMAN")) -> AMAN
A7: 6 | B7: SK-006 | C7: ='Master Inventory'!C7 -> Sunscreen SPF50 PA+++ 40ml | D7: ='Master Inventory'!J7 -> 300 | E7: =SUMIF('Sales - TikTok'!$E$2:$E$101,B7,'Sales - TikTok'!$G$2:$G$101) -> 17 | F7: =SUMIF('Sales - Shopee'!$E$2:$E$101,B7,'Sales - Shopee'!$G$2:$G$101) -> 6 | G7: =E7+F7 -> 23 | H7: =D7-G7 -> 277 | I7: =IF(H7<=0,"OUT OF STOCK",IF(H7<='Master Inventory'!K7,"LOW STOCK","AMAN")) -> AMAN
A8: 7 | B8: SK-007 | C8: ='Master Inventory'!C8 -> Eye Cream Anti Aging 15ml | D8: ='Master Inventory'!J8 -> 30 | E8: =SUMIF('Sales - TikTok'!$E$2:$E$101,B8,'Sales - TikTok'!$G$2:$G$101) -> 8 | F8: =SUMIF('Sales - Shopee'!$E$2:$E$101,B8,'Sales - Shopee'!$G$2:$G$101) -> 8 | G8: =E8+F8 -> 16 | H8: =D8-G8 -> 14 | I8: =IF(H8<=0,"OUT OF STOCK",IF(H8<='Master Inventory'!K8,"LOW STOCK","AMAN")) -> LOW STOCK
A9: 8 | B9: SK-008 | C9: ='Master Inventory'!C9 -> Sheet Mask Brightening (Box 5pcs) | D9: ='Master Inventory'!J9 -> 220 | E9: =SUMIF('Sales - TikTok'!$E$2:$E$101,B9,'Sales - TikTok'!$G$2:$G$101) -> 7 | F9: =SUMIF('Sales - Shopee'!$E$2:$E$101,B9,'Sales - Shopee'!$G$2:$G$101) -> 10 | G9: =E9+F9 -> 17 | H9: =D9-G9 -> 203 | I9: =IF(H9<=0,"OUT OF STOCK",IF(H9<='Master Inventory'!K9,"LOW STOCK","AMAN")) -> AMAN
A10: 9 | B10: MU-001 | C10: ='Master Inventory'!C10 -> Lip Tint Velvet Matte | D10: ='Master Inventory'!J10 -> 280 | E10: =SUMIF('Sales - TikTok'!$E$2:$E$101,B10,'Sales - TikTok'!$G$2:$G$101) -> 11 | F10: =SUMIF('Sales - Shopee'!$E$2:$E$101,B10,'Sales - Shopee'!$G$2:$G$101) -> 16 | G10: =E10+F10 -> 27 | H10: =D10-G10 -> 253 | I10: =IF(H10<=0,"OUT OF STOCK",IF(H10<='Master Inventory'!K10,"LOW STOCK","AMAN")) -> AMAN
A11: 10 | B11: MU-002 | C11: ='Master Inventory'!C11 -> Lip Cream Matte Long Lasting | D11: ='Master Inventory'!J11 -> 260 | E11: =SUMIF('Sales - TikTok'!$E$2:$E$101,B11,'Sales - TikTok'!$G$2:$G$101) -> 13 | F11: =SUMIF('Sales - Shopee'!$E$2:$E$101,B11,'Sales - Shopee'!$G$2:$G$101) -> 23 | G11: =E11+F11 -> 36 | H11: =D11-G11 -> 224 | I11: =IF(H11<=0,"OUT OF STOCK",IF(H11<='Master Inventory'!K11,"LOW STOCK","AMAN")) -> AMAN
A12: 11 | B12: MU-003 | C12: ='Master Inventory'!C12 -> Cushion Foundation SPF35 | D12: ='Master Inventory'!J12 -> 140 | E12: =SUMIF('Sales - TikTok'!$E$2:$E$101,B12,'Sales - TikTok'!$G$2:$G$101) -> 16 | F12: =SUMIF('Sales - Shopee'!$E$2:$E$101,B12,'Sales - Shopee'!$G$2:$G$101) -> 15 | G12: =E12+F12 -> 31 | H12: =D12-G12 -> 109 | I12: =IF(H12<=0,"OUT OF STOCK",IF(H12<='Master Inventory'!K12,"LOW STOCK","AMAN")) -> AMAN
A13: 12 | B13: MU-004 | C13: ='Master Inventory'!C13 -> Compact Powder Matte Finish | D13: ='Master Inventory'!J13 -> 130 | E13: =SUMIF('Sales - TikTok'!$E$2:$E$101,B13,'Sales - TikTok'!$G$2:$G$101) -> 2 | F13: =SUMIF('Sales - Shopee'!$E$2:$E$101,B13,'Sales - Shopee'!$G$2:$G$101) -> 5 | G13: =E13+F13 -> 7 | H13: =D13-G13 -> 123 | I13: =IF(H13<=0,"OUT OF STOCK",IF(H13<='Master Inventory'!K13,"LOW STOCK","AMAN")) -> AMAN
... A26: 25 | B26: FR-002 | C26: ='Master Inventory'!C26 -> Eau de Parfum 50ml | D26: ='Master Inventory'!J26 -> 50 | E26: =SUMIF('Sales - TikTok'!$E$2:$E$101,B26,'Sales - TikTok'!$G$2:$G$101) -> 6 | F26: =SUMIF('Sales - Shopee'!$E$2:$E$101,B26,'Sales - Shopee'!$G$2:$G$101) -> 47 | G26: =E26+F26 -> 53 | H26: =D26-G26 -> -3 | I26: =IF(H26<=0,"OUT OF STOCK",IF(H26<='Master Inventory'!K26,"LOW STOCK","AMAN")) -> OUT OF STOCK

Sheet Price List (Internal vs Ecommerce)
A1: No | B1: SKU | C1: Nama Produk | D1: COGS per Unit (Rp) | E1: Target Margin Internal (%) | F1: Harga Internal (Modal+Margin) (Rp) | G1: Rata2 Harga Jual Net TikTok (Rp) | H1: Rata2 Harga Jual Net Shopee (Rp) | I1: Gap TikTok vs Internal (%) | J1: Gap Shopee vs Internal (%) | K1: Status Harga TikTok | L1: Status Harga Shopee | M1: Keterangan
A2: 1 | B2: SK-001 | C2: ='Master Inventory'!C2 -> Facial Wash Gentle Foam 100ml | D2: ='Master Inventory'!F2 -> 16000 | E2: ='Master Inventory'!G2 -> 0.62 | F2: ='Master Inventory'!H2 -> 42000 | G2: =IFERROR(ROUND(AVERAGEIF('Sales - TikTok'!$E$2:$E$101,B2,'Sales - TikTok'!$J$2:$J$101),0),"TIDAK ADA DATA") -> 19300 | H2: =IFERROR(ROUND(AVERAGEIF('Sales - Shopee'!$E$2:$E$101,B2,'Sales - Shopee'!$J$2:$J$101),0),"TIDAK ADA DATA") -> 31757 | I2: =IFERROR((G2-F2)/F2,0) -> -0.540476 | J2: =IFERROR((H2-F2)/F2,0) -> -0.243881 | K2: =IF(ISTEXT(G2),"TIDAK ADA DATA",IF(G2<D2,"RUGI (DI BAWAH COGS)",IF(G2<F2,"DI BAWAH HARGA INTERNAL","SESUAI/DI ATAS INTERNAL"))) -> DI BAWAH HARGA INTERNAL | L2: =IF(ISTEXT(H2),"TIDAK ADA DATA",IF(H2<D2,"RUGI (DI BAWAH COGS)",IF(H2<F2,"DI BAWAH HARGA INTERNAL","SESUAI/DI ATAS INTERNAL"))) -> DI BAWAH HARGA INTERNAL | M2: Diskon melebihi target margin internal, cek kontribusi promo
A3: 2 | B3: SK-002 | C3: ='Master Inventory'!C3 -> Toner Hydrating Rose 150ml | D3: ='Master Inventory'!F3 -> 22000 | E3: ='Master Inventory'!G3 -> 0.62 | F3: ='Master Inventory'!H3 -> 58000 | G3: =IFERROR(ROUND(AVERAGEIF('Sales - TikTok'!$E$2:$E$101,B3,'Sales - TikTok'!$J$2:$J$101),0),"TIDAK ADA DATA") -> 18000 | H3: =IFERROR(ROUND(AVERAGEIF('Sales - Shopee'!$E$2:$E$101,B3,'Sales - Shopee'!$J$2:$J$101),0),"TIDAK ADA DATA") -> 43825 | I3: =IFERROR((G3-F3)/F3,0) -> -0.689655 | J3: =IFERROR((H3-F3)/F3,0) -> -0.244397 | K3: =IF(ISTEXT(G3),"TIDAK ADA DATA",IF(G3<D3,"RUGI (DI BAWAH COGS)",IF(G3<F3,"DI BAWAH HARGA INTERNAL","SESUAI/DI ATAS INTERNAL"))) -> RUGI (DI BAWAH COGS) | L3: =IF(ISTEXT(H3),"TIDAK ADA DATA",IF(H3<D3,"RUGI (DI BAWAH COGS)",IF(H3<F3,"DI BAWAH HARGA INTERNAL","SESUAI/DI ATAS INTERNAL"))) -> DI BAWAH HARGA INTERNAL | M3: Perlu review harga - ada channel yang jual di bawah COGS
A4: 3 | B4: SK-003 | C4: ='Master Inventory'!C4 -> Serum Vitamin C 20ml | D4: ='Master Inventory'!F4 -> 35000 | E4: ='Master Inventory'!G4 -> 0.62 | F4: ='Master Inventory'!H4 -> 92000 | G4: =IFERROR(ROUND(AVERAGEIF('Sales - TikTok'!$E$2:$E$101,B4,'Sales - TikTok'!$J$2:$J$101),0),"TIDAK ADA DATA") -> 66843 | H4: =IFERROR(ROUND(AVERAGEIF('Sales - Shopee'!$E$2:$E$101,B4,'Sales - Shopee'!$J$2:$J$101),0),"TIDAK ADA DATA") -> 104200 | I4: =IFERROR((G4-F4)/F4,0) -> -0.273446 | J4: =IFERROR((H4-F4)/F4,0) -> 0.132609 | K4: =IF(ISTEXT(G4),"TIDAK ADA DATA",IF(G4<D4,"RUGI (DI BAWAH COGS)",IF(G4<F4,"DI BAWAH HARGA INTERNAL","SESUAI/DI ATAS INTERNAL"))) -> DI BAWAH HARGA INTERNAL | L4: =IF(ISTEXT(H4),"TIDAK ADA DATA",IF(H4<D4,"RUGI (DI BAWAH COGS)",IF(H4<F4,"DI BAWAH HARGA INTERNAL","SESUAI/DI ATAS INTERNAL"))) -> SESUAI/DI ATAS INTERNAL | M4: Diskon melebihi target margin internal, cek kontribusi promo
A5: 4 | B5: SK-004 | C5: ='Master Inventory'!C5 -> Serum Niacinamide 10% 20ml | D5: ='Master Inventory'!F5 -> 32000 | E5: ='Master Inventory'!G5 -> 0.62 | F5: ='Master Inventory'!H5 -> 84000 | G5: =IFERROR(ROUND(AVERAGEIF('Sales - TikTok'!$E$2:$E$101,B5,'Sales - TikTok'!$J$2:$J$101),0),"TIDAK ADA DATA") -> 52320 | H5: =IFERROR(ROUND(AVERAGEIF('Sales - Shopee'!$E$2:$E$101,B5,'Sales - Shopee'!$J$2:$J$101),0),"TIDAK ADA DATA") -> 41267 | I5: =IFERROR((G5-F5)/F5,0) -> -0.377143 | J5: =IFERROR((H5-F5)/F5,0) -> -0.508726 | K5: =IF(ISTEXT(G5),"TIDAK ADA DATA",IF(G5<D5,"RUGI (DI BAWAH COGS)",IF(G5<F5,"DI BAWAH HARGA INTERNAL","SESUAI/DI ATAS INTERNAL"))) -> DI BAWAH HARGA INTERNAL | L5: =IF(ISTEXT(H5),"TIDAK ADA DATA",IF(H5<D5,"RUGI (DI BAWAH COGS)",IF(H5<F5,"DI BAWAH HARGA INTERNAL","SESUAI/DI ATAS INTERNAL"))) -> DI BAWAH HARGA INTERNAL | M5: Diskon melebihi target margin internal, cek kontribusi promo
A6: 5 | B6: SK-005 | C6: ='Master Inventory'!C6 -> Moisturizer Gel Cream 40g | D6: ='Master Inventory'!F6 -> 28000 | E6: ='Master Inventory'!G6 -> 0.62 | F6: ='Master Inventory'!H6 -> 74000 | G6: =IFERROR(ROUND(AVERAGEIF('Sales - TikTok'!$E$2:$E$101,B6,'Sales - TikTok'!$J$2:$J$101),0),"TIDAK ADA DATA") -> 62400 | H6: =IFERROR(ROUND(AVERAGEIF('Sales - Shopee'!$E$2:$E$101,B6,'Sales - Shopee'!$J$2:$J$101),0),"TIDAK ADA DATA") -> 61275 | I6: =IFERROR((G6-F6)/F6,0) -> -0.156757 | J6: =IFERROR((H6-F6)/F6,0) -> -0.171959 | K6: =IF(ISTEXT(G6),"TIDAK ADA DATA",IF(G6<D6,"RUGI (DI BAWAH COGS)",IF(G6<F6,"DI BAWAH HARGA INTERNAL","SESUAI/DI ATAS INTERNAL"))) -> DI BAWAH HARGA INTERNAL | L6: =IF(ISTEXT(H6),"TIDAK ADA DATA",IF(H6<D6,"RUGI (DI BAWAH COGS)",IF(H6<F6,"DI BAWAH HARGA INTERNAL","SESUAI/DI ATAS INTERNAL"))) -> DI BAWAH HARGA INTERNAL | M6: Diskon melebihi target margin internal, cek kontribusi promo
A7: 6 | B7: SK-006 | C7: ='Master Inventory'!C7 -> Sunscreen SPF50 PA+++ 40ml | D7: ='Master Inventory'!F7 -> 30000 | E7: ='Master Inventory'!G7 -> 0.62 | F7: ='Master Inventory'!H7 -> 79000 | G7: =IFERROR(ROUND(AVERAGEIF('Sales - TikTok'!$E$2:$E$101,B7,'Sales - TikTok'!$J$2:$J$101),0),"TIDAK ADA DATA") -> 49325 | H7: =IFERROR(ROUND(AVERAGEIF('Sales - Shopee'!$E$2:$E$101,B7,'Sales - Shopee'!$J$2:$J$101),0),"TIDAK ADA DATA") -> 46700 | I7: =IFERROR((G7-F7)/F7,0) -> -0.375633 | J7: =IFERROR((H7-F7)/F7,0) -> -0.408861 | K7: =IF(ISTEXT(G7),"TIDAK ADA DATA",IF(G7<D7,"RUGI (DI BAWAH COGS)",IF(G7<F7,"DI BAWAH HARGA INTERNAL","SESUAI/DI ATAS INTERNAL"))) -> DI BAWAH HARGA INTERNAL | L7: =IF(ISTEXT(H7),"TIDAK ADA DATA",IF(H7<D7,"RUGI (DI BAWAH COGS)",IF(H7<F7,"DI BAWAH HARGA INTERNAL","SESUAI/DI ATAS INTERNAL"))) -> DI BAWAH HARGA INTERNAL | M7: Diskon melebihi target margin internal, cek kontribusi promo
A8: 7 | B8: SK-007 | C8: ='Master Inventory'!C8 -> Eye Cream Anti Aging 15ml | D8: ='Master Inventory'!F8 -> 38000 | E8: ='Master Inventory'!G8 -> 0.62 | F8: ='Master Inventory'!H8 -> 100000 | G8: =IFERROR(ROUND(AVERAGEIF('Sales - TikTok'!$E$2:$E$101,B8,'Sales - TikTok'!$J$2:$J$101),0),"TIDAK ADA DATA") -> 64150 | H8: =IFERROR(ROUND(AVERAGEIF('Sales - Shopee'!$E$2:$E$101,B8,'Sales - Shopee'!$J$2:$J$101),0),"TIDAK ADA DATA") -> 103400 | I8: =IFERROR((G8-F8)/F8,0) -> -0.3585 | J8: =IFERROR((H8-F8)/F8,0) -> 0.034 | K8: =IF(ISTEXT(G8),"TIDAK ADA DATA",IF(G8<D8,"RUGI (DI BAWAH COGS)",IF(G8<F8,"DI BAWAH HARGA INTERNAL","SESUAI/DI ATAS INTERNAL"))) -> DI BAWAH HARGA INTERNAL | L8: =IF(ISTEXT(H8),"TIDAK ADA DATA",IF(H8<D8,"RUGI (DI BAWAH COGS)",IF(H8<F8,"DI BAWAH HARGA INTERNAL","SESUAI/DI ATAS INTERNAL"))) -> SESUAI/DI ATAS INTERNAL | M8: Diskon melebihi target margin internal, cek kontribusi promo
A9: 8 | B9: SK-008 | C9: ='Master Inventory'!C9 -> Sheet Mask Brightening (Box 5pcs) | D9: ='Master Inventory'!F9 -> 20000 | E9: ='Master Inventory'!G9 -> 0.62 | F9: ='Master Inventory'!H9 -> 53000 | G9: =IFERROR(ROUND(AVERAGEIF('Sales - TikTok'!$E$2:$E$101,B9,'Sales - TikTok'!$J$2:$J$101),0),"TIDAK ADA DATA") -> 55950 | H9: =IFERROR(ROUND(AVERAGEIF('Sales - Shopee'!$E$2:$E$101,B9,'Sales - Shopee'!$J$2:$J$101),0),"TIDAK ADA DATA") -> 17833 | I9: =IFERROR((G9-F9)/F9,0) -> 0.05566 | J9: =IFERROR((H9-F9)/F9,0) -> -0.663528 | K9: =IF(ISTEXT(G9),"TIDAK ADA DATA",IF(G9<D9,"RUGI (DI BAWAH COGS)",IF(G9<F9,"DI BAWAH HARGA INTERNAL","SESUAI/DI ATAS INTERNAL"))) -> SESUAI/DI ATAS INTERNAL | L9: =IF(ISTEXT(H9),"TIDAK ADA DATA",IF(H9<D9,"RUGI (DI BAWAH COGS)",IF(H9<F9,"DI BAWAH HARGA INTERNAL","SESUAI/DI ATAS INTERNAL"))) -> RUGI (DI BAWAH COGS) | M9: Perlu review harga - ada channel yang jual di bawah COGS
A10: 9 | B10: MU-001 | C10: ='Master Inventory'!C10 -> Lip Tint Velvet Matte | D10: ='Master Inventory'!F10 -> 14000 | E10: ='Master Inventory'!G10 -> 0.6 | F10: ='Master Inventory'!H10 -> 35000 | G10: =IFERROR(ROUND(AVERAGEIF('Sales - TikTok'!$E$2:$E$101,B10,'Sales - TikTok'!$J$2:$J$101),0),"TIDAK ADA DATA") -> 29225 | H10: =IFERROR(ROUND(AVERAGEIF('Sales - Shopee'!$E$2:$E$101,B10,'Sales - Shopee'!$J$2:$J$101),0),"TIDAK ADA DATA") -> 31280 | I10: =IFERROR((G10-F10)/F10,0) -> -0.165 | J10: =IFERROR((H10-F10)/F10,0) -> -0.106286 | K10: =IF(ISTEXT(G10),"TIDAK ADA DATA",IF(G10<D10,"RUGI (DI BAWAH COGS)",IF(G10<F10,"DI BAWAH HARGA INTERNAL","SESUAI/DI ATAS INTERNAL"))) -> DI BAWAH HARGA INTERNAL | L10: =IF(ISTEXT(H10),"TIDAK ADA DATA",IF(H10<D10,"RUGI (DI BAWAH COGS)",IF(H10<F10,"DI BAWAH HARGA INTERNAL","SESUAI/DI ATAS INTERNAL"))) -> DI BAWAH HARGA INTERNAL | M10: Diskon melebihi target margin internal, cek kontribusi promo
A11: 10 | B11: MU-002 | C11: ='Master Inventory'!C11 -> Lip Cream Matte Long Lasting | D11: ='Master Inventory'!F11 -> 15000 | E11: ='Master Inventory'!G11 -> 0.6 | F11: ='Master Inventory'!H11 -> 38000 | G11: =IFERROR(ROUND(AVERAGEIF('Sales - TikTok'!$E$2:$E$101,B11,'Sales - TikTok'!$J$2:$J$101),0),"TIDAK ADA DATA") -> 38125 | H11: =IFERROR(ROUND(AVERAGEIF('Sales - Shopee'!$E$2:$E$101,B11,'Sales - Shopee'!$J$2:$J$101),0),"TIDAK ADA DATA") -> 38820 | I11: =IFERROR((G11-F11)/F11,0) -> 0.003289 | J11: =IFERROR((H11-F11)/F11,0) -> 0.021579 | K11: =IF(ISTEXT(G11),"TIDAK ADA DATA",IF(G11<D11,"RUGI (DI BAWAH COGS)",IF(G11<F11,"DI BAWAH HARGA INTERNAL","SESUAI/DI ATAS INTERNAL"))) -> SESUAI/DI ATAS INTERNAL | L11: =IF(ISTEXT(H11),"TIDAK ADA DATA",IF(H11<D11,"RUGI (DI BAWAH COGS)",IF(H11<F11,"DI BAWAH HARGA INTERNAL","SESUAI/DI ATAS INTERNAL"))) -> SESUAI/DI ATAS INTERNAL | M11: Harga sesuai target margin internal
A12: 11 | B12: MU-003 | C12: ='Master Inventory'!C12 -> Cushion Foundation SPF35 | D12: ='Master Inventory'!F12 -> 45000 | E12: ='Master Inventory'!G12 -> 0.6 | F12: ='Master Inventory'!H12 -> 112000 | G12: =IFERROR(ROUND(AVERAGEIF('Sales - TikTok'!$E$2:$E$101,B12,'Sales - TikTok'!$J$2:$J$101),0),"TIDAK ADA DATA") -> 81112 | H12: =IFERROR(ROUND(AVERAGEIF('Sales - Shopee'!$E$2:$E$101,B12,'Sales - Shopee'!$J$2:$J$101),0),"TIDAK ADA DATA") -> 81783 | I12: =IFERROR((G12-F12)/F12,0) -> -0.275786 | J12: =IFERROR((H12-F12)/F12,0) -> -0.269795 | K12: =IF(ISTEXT(G12),"TIDAK ADA DATA",IF(G12<D12,"RUGI (DI BAWAH COGS)",IF(G12<F12,"DI BAWAH HARGA INTERNAL","SESUAI/DI ATAS INTERNAL"))) -> DI BAWAH HARGA INTERNAL | L12: =IF(ISTEXT(H12),"TIDAK ADA DATA",IF(H12<D12,"RUGI (DI BAWAH COGS)",IF(H12<F12,"DI BAWAH HARGA INTERNAL","SESUAI/DI ATAS INTERNAL"))) -> DI BAWAH HARGA INTERNAL | M12: Diskon melebihi target margin internal, cek kontribusi promo
A13: 12 | B13: MU-004 | C13: ='Master Inventory'!C13 -> Compact Powder Matte Finish | D13: ='Master Inventory'!F13 -> 25000 | E13: ='Master Inventory'!G13 -> 0.6 | F13: ='Master Inventory'!H13 -> 62000 | G13: =IFERROR(ROUND(AVERAGEIF('Sales - TikTok'!$E$2:$E$101,B13,'Sales - TikTok'!$J$2:$J$101),0),"TIDAK ADA DATA") -> 26100 | H13: =IFERROR(ROUND(AVERAGEIF('Sales - Shopee'!$E$2:$E$101,B13,'Sales - Shopee'!$J$2:$J$101),0),"TIDAK ADA DATA") -> 62000 | I13: =IFERROR((G13-F13)/F13,0) -> -0.579032 | J13: =IFERROR((H13-F13)/F13,0) -> 0 | K13: =IF(ISTEXT(G13),"TIDAK ADA DATA",IF(G13<D13,"RUGI (DI BAWAH COGS)",IF(G13<F13,"DI BAWAH HARGA INTERNAL","SESUAI/DI ATAS INTERNAL"))) -> DI BAWAH HARGA INTERNAL | L13: =IF(ISTEXT(H13),"TIDAK ADA DATA",IF(H13<D13,"RUGI (DI BAWAH COGS)",IF(H13<F13,"DI BAWAH HARGA INTERNAL","SESUAI/DI ATAS INTERNAL"))) -> SESUAI/DI ATAS INTERNAL | M13: Diskon melebihi target margin internal, cek kontribusi promo
... A26: 25 | B26: FR-002 | C26: ='Master Inventory'!C26 -> Eau de Parfum 50ml | D26: ='Master Inventory'!F26 -> 85000 | E26: ='Master Inventory'!G26 -> 0.65 | F26: ='Master Inventory'!H26 -> 243000 | G26: =IFERROR(ROUND(AVERAGEIF('Sales - TikTok'!$E$2:$E$101,B26,'Sales - TikTok'!$J$2:$J$101),0),"TIDAK ADA DATA") -> 160700 | H26: =IFERROR(ROUND(AVERAGEIF('Sales - Shopee'!$E$2:$E$101,B26,'Sales - Shopee'!$J$2:$J$101),0),"TIDAK ADA DATA") -> 168767 | I26: =IFERROR((G26-F26)/F26,0) -> -0.338683 | J26: =IFERROR((H26-F26)/F26,0) -> -0.305486 | K26: =IF(ISTEXT(G26),"TIDAK ADA DATA",IF(G26<D26,"RUGI (DI BAWAH COGS)",IF(G26<F26,"DI BAWAH HARGA INTERNAL","SESUAI/DI ATAS INTERNAL"))) -> DI BAWAH HARGA INTERNAL | L26: =IF(ISTEXT(H26),"TIDAK ADA DATA",IF(H26<D26,"RUGI (DI BAWAH COGS)",IF(H26<F26,"DI BAWAH HARGA INTERNAL","SESUAI/DI ATAS INTERNAL"))) -> DI BAWAH HARGA INTERNAL | M26: Diskon melebihi target margin internal, cek kontribusi promo
